cryptocompare_client/__init__.py
cryptocompare_client/core.py
cryptocompare_client/customized_methods.py
cryptocompare_client/masks.py
cryptocompare_client-0.1.4.dist-info/METADATA
cryptocompare_client-0.1.4.dist-info/RECORD
cryptocompare_client-0.1.4.dist-info/WHEEL
cryptocompare_client-0.1.4.dist-info/top_level.txt
